Workbook

Sheet Сегодня
B1: Оперативный отчёт | Z1: Дата: | AA1: =Данные!T4 -> 46126
B2: Operational report
B3: =Данные!E8&" "&Данные!E3 -> Apr' 2026
B5: Выручка ○ | F5: Заказы ○ | J5: Средний чек ○ | N5: Валовая прибыль ○ | S5: Валовая маржа ○ | W5: Возвраты ○
B6: vs yesterday | F6: vs yesterday | J6: vs yesterday | N6: vs yesterday | S6: vs yesterday | W6: vs yesterday
B9: =Данные!V4 -> 456149.43 | F9: =Данные!W4 -> 434 | J9: =Данные!X4 -> 1051.04 | N9: =Данные!Y4 -> 255547.83 | S9: =Данные!Z4 -> 0.5602 | W9: =TEXT(Данные!AB4,"# ##0")&" / "&Данные!AA4&" ед." -> 22 416 / 13 ед.
B10: =IF(C10>0,"k","l") -> l | C10: =Данные!V4/Данные!V5-1 -> -0.10845687 | D10: =Данные!V4-Данные!V5 -> -55490.91 | F10: =IF(G10>0,"k","l") -> l | G10: =Данные!W4/Данные!W5-1 -> -0.070663812 | H10: =Данные!W4-Данные!W5 -> -33 | J10: =IF(K10>0,"k","l") -> l | K10: =Данные!X4/Данные!X5-1 -> -0.040663022 | L10: =Данные!X4-Данные!X5 -> -44.55 | N10: =IF(O10>0,"k","l") -> l | O10: =Данные!Y4/Данные!Y5-1 -> -0.092691824 | P10: =Данные!Y4-Данные!Y5 -> -26107.11 | S10: =IF(T10>0,"k","l") -> k | T10: =Данные!Z4-Данные!Z5 -> 0.0097 | W10: =IF(X10>0,"k","l") -> k | X10: =Данные!AB4/Данные!AB5-1 -> 4.3332239 | Y10: =Данные!AB4-Данные!AB5 -> 18212.54
B13: Топ-5 товаров дня | L13: Промежуточные итоги месяца | U13: Факт vs план по форматам
B14: ID | C14: Название | D14: Формат | E14: Жанр | H14: Выручка | I14: Ед. | J14: Ранг | L14: KPI | O14: Значение | Q14: vs last month | R14: ∆ | U14: Формат | W14: Факт | X14: План | Y14: Выполнение
B15: =Данные!K4 -> 952 | C15: =Данные!L4 -> Annual Subscription | D15: =Данные!M4 -> Subscription | E15: =Данные!N4 -> Subscription | H15: =Данные!O4 -> 19950 | I15: =Данные!P4 -> 5 | J15: =Данные!Q4 -> 1 | L15: Выручка | N15: {=public_mart_mtd_pulse[mtd_revenue]} -> 6781347.2 | P15: =IF(Q15<0,Данные!$O$30,Данные!$O$29) -> ∨ | Q15: {=public_mart_mtd_pulse[mtd_revenue]/public_mart_mtd_pulse[prev_mtd_revenue]-1} -> -0.0008445253 | R15: {=public_mart_mtd_pulse[mtd_revenue]-public_mart_mtd_pulse[prev_mtd_revenue]} -> -5731.86 | U15: =Данные!G29 -> Audiobook | V15: =Данные!H29 -> 3385419.5 | X15: =Данные!I29 -> 7128427.4 | Y15: =V15/X15 -> 0.47491815
B16: =Данные!K5 -> 789 | C16: =Данные!L5 -> Падаль конструкция (History) | D16: =Данные!M5 -> Hardcover | E16: =Данные!N5 -> History | H16: =Данные!O5 -> 9796 | I16: =Данные!P5 -> 4 | J16: =Данные!Q5 -> 2 | L16: Заказы | N16: {=public_mart_mtd_pulse[mtd_orders]} -> 4234 | P16: =IF(Q16<0,Данные!$O$30,Данные!$O$29) -> ∧ | Q16: {=public_mart_mtd_pulse[mtd_orders]/public_mart_mtd_pulse[prev_mtd_orders]-1} -> 0.026175473 | R16: {=public_mart_mtd_pulse[mtd_orders]-public_mart_mtd_pulse[prev_mtd_orders]} -> 108 | U16: =Данные!G30 -> eBook | V16: =Данные!H30 -> 327 | X16: =Данные!I30 -> 3658.98 | Y16: =V16/X16 -> 0.089369168
B17: =Данные!K6 -> 888 | C17: =Данные!L6 -> Пастух ночь тысяча (Science) | D17: =Данные!M6 -> Audiobook | E17: =Данные!N6 -> Science | H17: =Данные!O6 -> 8838.08 | I17: =Данные!P6 -> 12 | J17: =Данные!Q6 -> 3 | L17: Средний чек | N17: {=public_mart_mtd_pulse[mtd_avg_order_value]} -> 1601.64 | P17: =IF(Q17<0,Данные!$O$30,Данные!$O$29) -> ∨ | Q17: {=public_mart_mtd_pulse[mtd_avg_order_value]/public_mart_mtd_pulse[prev_mtd_avg_order_value]-1} -> -0.026329068 | R17: {=public_mart_mtd_pulse[mtd_avg_order_value]-public_mart_mtd_pulse[prev_mtd_avg_order_value]} -> -43.31 | U17: =Данные!G31 -> Hardcover | V17: =Данные!H31 -> 2673599.3 | X17: =Данные!I31 -> 6395943.5 | Y17: =V17/X17 -> 0.41801484
B18: =Данные!K7 -> 749 | C18: =Данные!L7 -> Нож скользить (Science) | D18: =Данные!M7 -> Hardcover | E18: =Данные!N7 -> Science | H18: =Данные!O7 -> 8365 | I18: =Данные!P7 -> 5 | J18: =Данные!Q7 -> 4 | L18: Продано штук | N18: {=public_mart_mtd_pulse[mtd_net_qty]} -> 9446 | P18: =IF(Q18<0,Данные!$O$30,Данные!$O$29) -> ∧ | Q18: {=public_mart_mtd_pulse[mtd_net_qty]/public_mart_mtd_pulse[prev_mtd_net_qty]-1} -> 0.022073144 | R18: {=public_mart_mtd_pulse[mtd_net_qty]-public_mart_mtd_pulse[prev_mtd_net_qty]} -> 204 | U18: =Данные!G32 -> Paperback | V18: =Данные!H32 -> 238812.33 | X18: =Данные!I32 -> 590435.9 | Y18: =V18/X18 -> 0.40446783
B19: =Данные!K8 -> 755 | C19: =Данные!L8 -> Роскошный добиться (Mystery) | D19: =Данные!M8 -> Hardcover | E19: =Данные!N8 -> Mystery | H19: =Данные!O8 -> 7413 | I19: =Данные!P8 -> 6 | J19: =Данные!Q8 -> 5 | L19: Валовая прибыль | N19: {=public_mart_mtd_pulse[mtd_gross_profit]} -> 3808747.6 | P19: =IF(Q19<0,Данные!$O$30,Данные!$O$29) -> ∧ | Q19: {=public_mart_mtd_pulse[mtd_gross_profit]/public_mart_mtd_pulse[prev_mtd_gross_profit]-1} -> 0.0029812136 | R19: {=public_mart_mtd_pulse[mtd_gross_profit]-public_mart_mtd_pulse[prev_mtd_gross_profit]} -> 11320.94
L20: Валовая маржа | N20: {=public_mart_mtd_pulse[mtd_gross_margin]} -> 0.5617 | P20: =IF(Q20<0,Данные!$O$30,Данные!$O$29) -> ∧ | Q20: {=public_mart_mtd_pulse[mtd_gross_margin]-public_mart_mtd_pulse[prev_mtd_gross_margin]} -> 0.0022
B21: Тренды продаж | U21: Факт vs план по жанрам | AA21: Доля возвратов в выручке
U22: Жанр | W22: Факт | X22: План | Y22: Выполнение | AA22: =Данные!AB4/Данные!V4 -> 0.049140783
L23: Выполнение плана | U23: =Данные!G15 -> Biography | V23: =Данные!H15 -> 570899.41 | X23: =Данные!I15 -> 1180062.5 | Y23: =V23/X23 -> 0.48378743
U24: =Данные!G16 -> Business | V24: =Данные!H16 -> 387079.23 | X24: =Данные!I16 -> 857437.08 | Y24: =V24/X24 -> 0.45143747
L25: Факт | M25: =GETPIVOTDATA("[Measures].[Сумма по столбцу fact_amount]",Данные!$G$5) -> 6298158.2 | Q25: =Данные!G9 -> 0.44609367 | U25: =Данные!G17 -> Children | V25: =Данные!H17 -> 835334.01 | X25: =Данные!I17 -> 1863203.4 | Y25: =V25/X25 -> 0.44833215
L26: План | M26: =GETPIVOTDATA("[Measures].[Сумма по столбцу plan_amount]",Данные!$G$5) -> 14118466 | U26: =Данные!G18 -> Fantasy | V26: =Данные!H18 -> 740545.76 | X26: =Данные!I18 -> 1708479.7 | Y26: =V26/X26 -> 0.43345307
L27: Осталось | M27: =M26-M25 -> 7820307.6 | U27: =Данные!G19 -> Fiction | V27: =Данные!H19 -> 589200.25 | X27: =Данные!I19 -> 1335500.7 | Y27: =V27/X27 -> 0.44118304
U28: =Данные!G20 -> History | V28: =Данные!H20 -> 479000.99 | X28: =Данные!I20 -> 1072568 | Y28: =V28/X28 -> 0.44659266
U29: =Данные!G21 -> Mystery | V29: =Данные!H21 -> 597056.37 | X29: =Данные!I21 -> 1385769.7 | Y29: =V29/X29 -> 0.4308482
L30: Прогноз закрытия месяца | P30: =M25/Данные!E5*Данные!E6 -> 13496053 | R30: =P30/M26 -> 0.955915 | U30: =Данные!G22 -> Poetry | V30: =Данные!H22 -> 667693.18 | X30: =Данные!I22 -> 1571101.2 | Y30: =V30/X30 -> 0.42498418
L31: Отклонение | P31: =M26-P30 -> 622412.55 | U31: =Данные!G23 -> Romance | V31: =Данные!H23 -> 728848.48 | X31: =Данные!I23 -> 1714514.2 | Y31: =V31/X31 -> 0.42510495
U32: =Данные!G24 -> Science | V32: =Данные!H24 -> 702500.51 | X32: =Данные!I24 -> 1429829.3 | Y32: =V32/X32 -> 0.49131774
L34: *KPI — чистая выручка (за вычетом возвратов)
B37: Low-stock виджет — Товары ниже порога остатков
B38: product_id | C38: title | D38: format | E38: genre | F38: publisher | G38: price_rub | H38: closing_stock | I38: is_low_stock | J38: stock_date | K38: avg_daily_sales_30d | L38: days_until_stockout | M38: recommended_order_qty | N38: recommended_order_cost | O38: alert_level

Sheet Данные
B2: Даты месяца | D2: Сегодня | E2: =T4 -> 46126 | G2: План vs Факт | K2: Топ-5 товаров дня | S2: KPI текущего и прошлого дня
B3: {=DATE(E3,E4,1)+_xlfn.SEQUENCE(DAY(EOMONTH(DATE(E3,E4,1),0)),,0)} -> 46113 | D3: Год | E3: =YEAR(E2) -> 2026 | K3: product_id | L3: title | M3: format | N3: genre | O3: revenue | P3: net_qty | Q3: rnk | S3: day_type | T3: report_date | U3: prev_date | V3: total_revenue | W3: total_orders | X3: avg_order_value | Y3: total_gross_profit | Z3: gross_margin | AA3: return_qty | AB3: return_amount | AC3: return_rate_pct | AD3: promo_orders | AE3: promo_revenue | AF3: promo_orders_pct | AG3: lost_sales_qty
B4: 46114 | D4: Месяц | E4: =MONTH(E2) -> 4 | G4: За месяц | K4: 952 | L4: Annual Subscription | M4: Subscription | N4: Subscription | O4: 19950 | P4: 5 | Q4: 1 | S4: today | T4: 46126 | U4: 46125 | V4: 456149.43 | W4: 434 | X4: 1051.04 | Y4: 255547.83 | Z4: 0.5602 | AA4: 13 | AB4: 22415.54 | AC4: 4.7 | AD4: 59 | AE4: 61295.78 | AF4: 13.6 | AG4: 0
B5: 46115 | D5: День | E5: =DAY(E2) -> 14 | G5: Факт | H5: План | K5: 789 | L5: Падаль конструкция (History) | M5: Hardcover | N5: History | O5: 9796 | P5: 4 | Q5: 2 | S5: yesterday | T5: 46125 | U5: 46124 | V5: 511640.34 | W5: 467 | X5: 1095.59 | Y5: 281654.94 | Z5: 0.5505 | AA5: 3 | AB5: 4203 | AC5: 0.8 | AD5: 59 | AE5: 90005.34 | AF5: 12.6 | AG5: 0
B6: 46116 | D6: Всего дней | E6: =COUNT(B3:B33) -> 30 | G6: 6298158.2 | H6: 14118466 | K6: 888 | L6: Пастух ночь тысяча (Science) | M6: Audiobook | N6: Science | O6: 8838.08 | P6: 12 | Q6: 3
B7: 46117 | K7: 749 | L7: Нож скользить (Science) | M7: Hardcover | N7: Science | O7: 8365 | P7: 5 | Q7: 4 | S7: Накопительный итог текущего месяца
B8: 46118 | D8: Месяц | E8: =VLOOKUP(E4,D9:E20,2,0) -> Apr' | G8: Выполнение | K8: 755 | L8: Роскошный добиться (Mystery) | M8: Hardcover | N8: Mystery | O8: 7413 | P8: 6 | Q8: 5 | S8: month_start | T8: month_to_date | U8: mtd_revenue | V8: mtd_orders | W8: mtd_net_qty | X8: mtd_gross_profit | Y8: mtd_gross_margin | Z8: mtd_avg_order_value | AA8: prev_mtd_revenue | AB8: prev_mtd_orders | AC8: prev_mtd_net_qty | AD8: prev_mtd_gross_profit | AE8: prev_mtd_gross_margin | AF8: prev_mtd_avg_order_value
B9: 46119 | D9: 1 | E9: Jan' | G9: =GETPIVOTDATA("[Measures].[Сумма по столбцу fact_amount]",$G$5)/GETPIVOTDATA("[Measures].[Сумма по столбцу plan_amount]",$G$5) -> 0.44609367 | H9: Выполнено | S9: 46113 | T9: 46126 | U9: 6781347.2 | V9: 4234 | W9: 9446 | X9: 3808747.6 | Y9: 0.5617 | Z9: 1601.64 | AA9: 6787079 | AB9: 4126 | AC9: 9242 | AD9: 3797426.7 | AE9: 0.5595 | AF9: 1644.95
B10: 46120 | D10: 2 | E10: Feb' | G10: =1-G9 -> 0.55390633 | H10: Осталось | K10: Выручка по дням текущего месяца
B11: 46121 | D11: 3 | E11: Mar' | K11: Дата | L11: Чистая выручка | M11: Валовая прибыль | N11: Заказы | O11: План продаж | S11: Структура по каналам
B12: 46122 | D12: 4 | E12: Apr' | K12: 46113 | L12: 477417.99 | M12: 274303.94 | N12: 306 | O12: 470615.53 | S12: day_type | T12: report_date | U12: channel | V12: orders | W12: net_qty | X12: net_revenue | Y12: gross_profit | Z12: gross_margin | AA12: promo_orders | AB12: promo_revenue | AC12: promo_orders_pct
B13: 46123 | D13: 5 | E13: May' | G13: По жанрам | K13: 46114 | L13: 457417.23 | M13: 267560.88 | N13: 276 | O13: 470615.53 | S13: yesterday | T13: 46125 | U13: API Partner | V13: 47 | W13: 79 | X13: 50227.73 | Y13: 28293.93 | Z13: 0.5633 | AA13: 5 | AB13: 4906.73 | AC13: 10.6
B14: 46124 | D14: 6 | E14: Jun' | G14: Жанр | H14: Факт | I14: План | K14: 46115 | L14: 540786.09 | M14: 313030.34 | N14: 332 | O14: 470615.53 | S14: yesterday | T14: 46125 | U14: Mobile App | V14: 141 | W14: 254 | X14: 181660.08 | Y14: 99002.38 | Z14: 0.545 | AA14: 22 | AB14: 24852.08 | AC14: 15.6
B15: 46125 | D15: 7 | E15: Jul' | G15: Biography | H15: 570899.41 | I15: 1180062.5 | K15: 46116 | L15: 527045.55 | M15: 284616.9 | N15: 310 | O15: 470615.53 | S15: yesterday | T15: 46125 | U15: Web | V15: 200 | W15: 373 | X15: 279752.53 | Y15: 154358.63 | Z15: 0.5518 | AA15: 32 | AB15: 60246.53 | AC15: 16
B16: 46126 | D16: 8 | E16: Aug' | G16: Business | H16: 387079.23 | I16: 857437.08 | K16: 46117 | L16: 473509.46 | M16: 264130.76 | N16: 303 | O16: 470615.53 | S16: today | T16: 46126 | U16: API Partner | V16: 35 | W16: 57 | X16: 29538.46 | Y16: 16759.66 | Z16: 0.5674 | AA16: 7 | AB16: 8111.46 | AC16: 20
B17: 46127 | D17: 9 | E17: Sep' | G17: Children | H17: 835334.01 | I17: 1863203.4 | K17: 46118 | L17: 480800.75 | M17: 272374.1 | N17: 301 | O17: 470615.53 | S17: today | T17: 46126 | U17: Mobile App | V17: 138 | W17: 227 | X17: 179215.48 | Y17: 103344.18 | Z17: 0.5766 | AA17: 17 | AB17: 20597.48 | AC17: 12.3
B18: 46128 | D18: 10 | E18: Okt' | G18: Fantasy | H18: 740545.76 | I18: 1708479.7 | K18: 46119 | L18: 565194.02 | M18: 317143.12 | N18: 324 | O18: 470615.53 | S18: today | T18: 46126 | U18: Web | V18: 187 | W18: 381 | X18: 247395.49 | Y18: 135443.99 | Z18: 0.5475 | AA18: 35 | AB18: 32586.84 | AC18: 18.7
B19: 46129 | D19: 11 | E19: Nov' | G19: Fiction | H19: 589200.25 | I19: 1335500.7 | K19: 46120 | L19: 481399.15 | M19: 269888.3 | N19: 297 | O19: 470615.53
B20: 46130 | D20: 12 | E20: Dec' | G20: History | H20: 479000.99 | I20: 1072568 | K20: 46121 | L20: 452385.45 | M20: 255173.65 | N20: 322 | O20: 470615.53 | S20: Стурктура по форматам
B21: 46131 | G21: Mystery | H21: 597056.37 | I21: 1385769.7 | K21: 46122 | L21: 435220.77 | M21: 243035.12 | N21: 279 | O21: 470615.53 | S21: day_type | T21: format | U21: orders | V21: net_qty | W21: net_revenue | X21: gross_profit | Y21: gross_margin | Z21: return_qty | AA21: return_amount | AB21: promo_orders | AC21: promo_revenue | AD21: lost_sales_qty
B22: 46132 | D22: k | G22: Poetry | H22: 667693.18 | I22: 1571101.2 | K22: 46123 | L22: 487648.31 | M22: 265837.71 | N22: 283 | O22: 470615.53 | S22: today | T22: Audiobook | U22: 242 | V22: 518 | W22: 242151.33 | X22: 153416.53 | Y22: 0.6336 | Z22: 0 | AA22: 0 | AB22: 50 | AC22: 44542.68 | AD22: 0
B23: 46133 | D23: l | G23: Romance | H23: 728848.48 | I23: 1714514.2 | K23: 46124 | L23: 434732.65 | M23: 244450.05 | N23: 292 | O23: 470615.53 | S23: today | T23: Hardcover | U23: 76 | V23: 117 | W23: 177725.1 | X23: 77208.2 | Y23: 0.4344 | Z23: 13 | AA23: 22415.54 | AB23: 9 | AC23: 16753.1 | AD23: 0
B24: 46134 | G24: Science | H24: 702500.51 | I24: 1429829.3 | K24: 46125 | L24: 511640.34 | M24: 281654.94 | N24: 317 | O24: 470615.53 | S24: today | T24: Paperback | U24: 11 | V24: 17 | W24: 13131 | X24: 5252.4 | Y24: 0.4 | Z24: 0 | AA24: 0 | AB24: 0 | AC24: 0 | AD24: 0
B25: 46135 | G25: Общий итог | H25: 6298158.2 | I25: 14118466 | K25: 46126 | L25: 456149.43 | M25: 255547.83 | N25: 292 | O25: 470615.53 | S25: today | T25: Subscription | U25: 8 | V25: 13 | W25: 23142 | X25: 19670.7 | Y25: 0.85 | Z25: 0 | AA25: 0 | AB25: 0 | AC25: 0 | AD25: 0
B26: 46136 | S26: yesterday | T26: Audiobook | U26: 258 | V26: 522 | W26: 248689.46 | X26: 157827.01 | Y26: 0.6346 | Z26: 0 | AA26: 0 | AB26: 41 | AC26: 40969.46 | AD26: 0
B27: 46137 | G27: По форматам | S27: yesterday | T27: Hardcover | U27: 85 | V27: 134 | W27: 209502.69 | X27: 89574.64 | Y27: 0.4276 | Z27: 1 | AA27: 2366 | AB27: 14 | AC27: 34140.69 | AD27: 0
B28: 46138 | G28: Жанр | H28: Факт | I28: План | S28: yesterday | T28: Paperback | U28: 20 | V28: 30 | W28: 23922.19 | X28: 9156.19 | Y28: 0.3827 | Z28: 2 | AA28: 1837 | AB28: 3 | AC28: 2925.19 | AD28: 0
B29: 46139 | G29: Audiobook | H29: 3385419.5 | I29: 7128427.4 | O29: ∧ | S29: yesterday | T29: Subscription | U29: 12 | V29: 20 | W29: 29526 | X29: 25097.1 | Y29: 0.85 | Z29: 0 | AA29: 0 | AB29: 1 | AC29: 11970 | AD29: 0
B30: 46140 | G30: eBook | H30: 327 | I30: 3658.98 | O30: ∨
B31: 46141 | G31: Hardcover | H31: 2673599.3 | I31: 6395943.5
B32: 46142 | G32: Paperback | H32: 238812.33 | I32: 590435.9
G33: Общий итог | H33: 6298158.2 | I33: 14118466
